{
    "include": [
        "pop_sPY"
    ],
    "saveData": "../data/v0_batch0/v0_batch0_3_1_rate.json",
    "saveFig": true,
    "showFig": true,
    "statData": [
        [
            280.40000000000003,
            293.6,
            275.8,
            270.8,
            297.6,
            255.60000000000002,
            243.20000000000002,
            288.40000000000003,
            290.6,
            288.6,
            228.20000000000002,
            233.8,
            227.20000000000002,
            261.2,
            272.8,
            260.6,
            261.0,
            251.0,
            226.60000000000002,
            289.40000000000003,
            240.8,
            266.0,
            259.2,
            310.20000000000005,
            290.0,
            270.8,
            294.0,
            295.8,
            293.40000000000003,
            225.60000000000002,
            281.40000000000003,
            247.0,
            236.8,
            236.4,
            285.6,
            298.8,
            299.8,
            254.60000000000002,
            332.8,
            256.40000000000003,
            241.60000000000002,
            289.2,
            269.0,
            234.0,
            291.0,
            267.8,
            303.8,
            272.8,
            210.60000000000002,
            283.40000000000003,
            321.8,
            279.2,
            284.40000000000003,
            241.60000000000002,
            313.20000000000005,
            270.0,
            226.8,
            278.40000000000003,
            272.6,
            240.8,
            278.40000000000003,
            278.40000000000003,
            286.8,
            267.6,
            299.2,
            296.6,
            254.4,
            314.8,
            296.40000000000003,
            252.8,
            301.40000000000003,
            286.0,
            254.8,
            292.6,
            251.20000000000002,
            270.6,
            251.60000000000002,
            260.40000000000003,
            226.8,
            301.2,
            304.0,
            294.8,
            285.40000000000003,
            276.2,
            258.2,
            300.6,
            275.6,
            241.0,
            267.0,
            275.0,
            281.8,
            300.2,
            239.4,
            290.2,
            310.20000000000005,
            281.8,
            323.0,
            225.4,
            271.8,
            304.0,
            286.2,
            283.8,
            256.40000000000003,
            258.6,
            276.2,
            296.40000000000003,
            293.8,
            201.60000000000002,
            302.8,
            276.0,
            284.8,
            250.8,
            285.2,
            284.0,
            253.60000000000002,
            288.40000000000003,
            268.2,
            281.0,
            299.40000000000003,
            267.0,
            290.0,
            271.8,
            299.8,
            265.0,
            295.6,
            280.8,
            276.2,
            278.2,
            298.0,
            302.2,
            305.6,
            272.8,
            272.6,
            281.0,
            278.6,
            273.0,
            235.60000000000002,
            253.4,
            284.6,
            268.2,
            286.2,
            257.6,
            316.0,
            230.60000000000002,
            258.6,
            266.0,
            291.8,
            283.6,
            241.0,
            281.6,
            295.0,
            296.8,
            273.0,
            241.0,
            261.6,
            289.6,
            270.0,
            215.20000000000002,
            254.60000000000002,
            280.6,
            316.20000000000005,
            273.40000000000003,
            287.0,
            299.8,
            310.0,
            272.6,
            300.2,
            245.0,
            258.0,
            302.8,
            274.8,
            272.0,
            283.40000000000003,
            292.8,
            285.40000000000003,
            289.0,
            251.0,
            299.6,
            246.60000000000002,
            295.0,
            259.0,
            284.8,
            248.4,
            255.4,
            318.20000000000005,
            263.8,
            275.2,
            305.8,
            320.6,
            263.2,
            301.40000000000003,
            261.2,
            247.0,
            289.0,
            231.4,
            275.0,
            257.0,
            269.0,
            223.60000000000002,
            254.60000000000002
        ]
    ],
    "timeRange": [
        0,
        5000.0
    ]
}